tunex/__init__.py
tunex/__main__.py
tunex/config.py
tunex/tokenizer.py
tunex/chat/__init__.py
tunex/chat/main.py
tunex/models/__init__.py
tunex/models/gpt2/__init__.py
tunex/models/gpt2/model.py
tunex/modules/__init__.py
tunex/modules/attention.py
tunex/modules/mlp.py
tunex/text_generation/__init__.py
tunex/text_generation/main.py
tunex/utils/__init__.py
tunex/utils/convert_from_hf_weights.py
tunex/utils/download.py
tunex/utils/utilities.py
tunex-0.1.3.dist-info/LICENSE
tunex-0.1.3.dist-info/METADATA
tunex-0.1.3.dist-info/WHEEL
tunex-0.1.3.dist-info/entry_points.txt
tunex-0.1.3.dist-info/top_level.txt
tunex-0.1.3.dist-info/RECORD
