Metadata-Version: 2.1
Name: tunex
Version: 0.1.3
Summary: A powerful CLI toolkit offering one shot solution for LLM in running, finetuning and instruction tuning
Author-email: swayaminsync <hawkempire007@gmail.com>
License: Apache-2.0
Project-URL: homepage, https://github.com/swayaminsync/tunex
License-File: LICENSE
Requires-Dist: torch ==2.2.2
Requires-Dist: pyyaml ==6.0.1
Requires-Dist: pyfiglet ==0.8.post1
Requires-Dist: numpy ==1.24.4
Requires-Dist: jsonargparse ==4.29.0
Requires-Dist: tokenizers ==0.19.1
Requires-Dist: huggingface-hub >=0.23.4
Requires-Dist: accelerate ==0.31.0
Requires-Dist: transformers ==4.41.2
